[
  {
    "id":1001,
    "value":312
  },
  {
    "id":1003,
    "value":343
  },
  {
    "id":1005,
    "value":214
  },
  {
    "id":1007,
    "value":93
  },
  {
    "id":1009,
    "value":87
  },
  {
    "id":1011,
    "value":253
  },
  {
    "id":1013,
    "value":484
  },
  {
    "id":1015,
    "value":184
  },
  {
    "id":1017,
    "value":417
  },
  {
    "id":1019,
    "value":42
  },
  {
    "id":1021,
    "value":121
  },
  {
    "id":1023,
    "value":162
  },
  {
    "id":1025,
    "value":165
  },
  {
    "id":1027,
    "value":30
  },
  {
    "id":1029,
    "value":20
  },
  {
    "id":1031,
    "value":260
  },
  {
    "id":1033,
    "value":230
  },
  {
    "id":1035,
    "value":70
  },
  {
    "id":1037,
    "value":43
  },
  {
    "id":1039,
    "value":98
  },
  {
    "id":1041,
    "value":99
  },
  {
    "id":1043,
    "value":220
  },
  {
    "id":1045,
    "value":149
  },
  {
    "id":1047,
    "value":406
  },
  {
    "id":1049,
    "value":291
  },
  {
    "id":1051,
    "value":471
  },
  {
    "id":1053,
    "value":93
  },
  {
    "id":1055,
    "value":287
  },
  {
    "id":1057,
    "value":23
  },
  {
    "id":1059,
    "value":652
  },
  {
    "id":1061,
    "value":46
  },
  {
    "id":1063,
    "value":112
  },
  {
    "id":1065,
    "value":219
  },
  {
    "id":1067,
    "value":94
  },
  {
    "id":1069,
    "value":270
  },
  {
    "id":1071,
    "value":107
  },
  {
    "id":1073,
    "value":2250
  },
  {
    "id":1075,
    "value":30
  },
  {
    "id":1077,
    "value":207
  },
  {
    "id":1079,
    "value":60
  },
  {
    "id":1081,
    "value":625
  },
  {
    "id":1083,
    "value":162
  },
  {
    "id":1085,
    "value":326
  },
  {
    "id":1087,
    "value":110
  },
  {
    "id":1089,
    "value":428
  },
  {
    "id":1091,
    "value":200
  },
  {
    "id":1093,
    "value":129
  },
  {
    "id":1095,
    "value":786
  },
  {
    "id":1097,
    "value":2593
  },
  {
    "id":1099,
    "value":95
  },
  {
    "id":1101,
    "value":2436
  },
  {
    "id":1103,
    "value":477
  },
  {
    "id":1105,
    "value":56
  },
  {
    "id":1107,
    "value":131
  },
  {
    "id":1109,
    "value":283
  },
  {
    "id":1111,
    "value":137
  },
  {
    "id":1113,
    "value":250
  },
  {
    "id":1115,
    "value":153
  },
  {
    "id":1117,
    "value":580
  },
  {
    "id":1119,
    "value":253
  },
  {
    "id":1121,
    "value":146
  },
  {
    "id":1123,
    "value":454
  },
  {
    "id":1125,
    "value":1070
  },
  {
    "id":1127,
    "value":500
  },
  {
    "id":1129,
    "value":84
  },
  {
    "id":1131,
    "value":190
  },
  {
    "id":1133,
    "value":106
  },
  {
    "id":80001,
    "value":0
  },
  {
    "id":90001,
    "value":371
  }
]