[
  {
    "id":4001,
    "value":1214
  },
  {
    "id":4003,
    "value":64
  },
  {
    "id":4005,
    "value":1041
  },
  {
    "id":4007,
    "value":24
  },
  {
    "id":4009,
    "value":24
  },
  {
    "id":4011,
    "value":3
  },
  {
    "id":4012,
    "value":51
  },
  {
    "id":4013,
    "value":8448
  },
  {
    "id":4015,
    "value":329
  },
  {
    "id":4017,
    "value":1550
  },
  {
    "id":4019,
    "value":2075
  },
  {
    "id":4021,
    "value":766
  },
  {
    "id":4023,
    "value":187
  },
  {
    "id":4025,
    "value":291
  },
  {
    "id":4027,
    "value":797
  },
  {
    "id":80004,
    "value":0
  },
  {
    "id":90004,
    "value":0
  }
]