[
  {
    "id":17001,
    "value":67
  },
  {
    "id":17003,
    "value":21
  },
  {
    "id":17005,
    "value":12
  },
  {
    "id":17007,
    "value":560
  },
  {
    "id":17009,
    "value":10
  },
  {
    "id":17011,
    "value":24
  },
  {
    "id":17013,
    "value":1
  },
  {
    "id":17015,
    "value":21
  },
  {
    "id":17017,
    "value":117
  },
  {
    "id":17019,
    "value":801
  },
  {
    "id":17021,
    "value":42
  },
  {
    "id":17023,
    "value":14
  },
  {
    "id":17025,
    "value":2
  },
  {
    "id":17027,
    "value":224
  },
  {
    "id":17029,
    "value":154
  },
  {
    "id":17031,
    "value":88138
  },
  {
    "id":17033,
    "value":18
  },
  {
    "id":17035,
    "value":10
  },
  {
    "id":17037,
    "value":527
  },
  {
    "id":17039,
    "value":4
  },
  {
    "id":17041,
    "value":43
  },
  {
    "id":17043,
    "value":8780
  },
  {
    "id":17045,
    "value":7
  },
  {
    "id":17047,
    "value":2
  },
  {
    "id":17049,
    "value":12
  },
  {
    "id":17051,
    "value":23
  },
  {
    "id":17053,
    "value":26
  },
  {
    "id":17055,
    "value":12
  },
  {
    "id":17057,
    "value":15
  },
  {
    "id":17059,
    "value":2
  },
  {
    "id":17061,
    "value":9
  },
  {
    "id":17063,
    "value":144
  },
  {
    "id":17065,
    "value":2
  },
  {
    "id":17067,
    "value":18
  },
  {
    "id":17069,
    "value":1
  },
  {
    "id":17071,
    "value":8
  },
  {
    "id":17073,
    "value":77
  },
  {
    "id":17075,
    "value":144
  },
  {
    "id":17077,
    "value":325
  },
  {
    "id":17079,
    "value":46
  },
  {
    "id":17081,
    "value":107
  },
  {
    "id":17083,
    "value":33
  },
  {
    "id":17085,
    "value":39
  },
  {
    "id":17087,
    "value":20
  },
  {
    "id":17089,
    "value":7496
  },
  {
    "id":17091,
    "value":1168
  },
  {
    "id":17093,
    "value":928
  },
  {
    "id":17095,
    "value":119
  },
  {
    "id":17097,
    "value":9447
  },
  {
    "id":17099,
    "value":195
  },
  {
    "id":17101,
    "value":6
  },
  {
    "id":17103,
    "value":96
  },
  {
    "id":17105,
    "value":40
  },
  {
    "id":17107,
    "value":13
  },
  {
    "id":17109,
    "value":101
  },
  {
    "id":17111,
    "value":1937
  },
  {
    "id":17113,
    "value":253
  },
  {
    "id":17115,
    "value":223
  },
  {
    "id":17117,
    "value":48
  },
  {
    "id":17119,
    "value":841
  },
  {
    "id":17121,
    "value":63
  },
  {
    "id":17123,
    "value":6
  },
  {
    "id":17125,
    "value":21
  },
  {
    "id":17127,
    "value":8
  },
  {
    "id":17129,
    "value":23
  },
  {
    "id":17131,
    "value":20
  },
  {
    "id":17133,
    "value":117
  },
  {
    "id":17135,
    "value":41
  },
  {
    "id":17137,
    "value":123
  },
  {
    "id":17139,
    "value":15
  },
  {
    "id":17141,
    "value":238
  },
  {
    "id":17143,
    "value":447
  },
  {
    "id":17145,
    "value":46
  },
  {
    "id":17147,
    "value":17
  },
  {
    "id":17149,
    "value":2
  },
  {
    "id":17151,
    "value":1
  },
  {
    "id":17153,
    "value":67
  },
  {
    "id":17155,
    "value":1
  },
  {
    "id":17157,
    "value":278
  },
  {
    "id":17159,
    "value":4
  },
  {
    "id":17161,
    "value":809
  },
  {
    "id":17163,
    "value":1671
  },
  {
    "id":17165,
    "value":8
  },
  {
    "id":17167,
    "value":397
  },
  {
    "id":17169,
    "value":13
  },
  {
    "id":17171,
    "value":0
  },
  {
    "id":17173,
    "value":16
  },
  {
    "id":17175,
    "value":3
  },
  {
    "id":17177,
    "value":257
  },
  {
    "id":17179,
    "value":113
  },
  {
    "id":17181,
    "value":182
  },
  {
    "id":17183,
    "value":50
  },
  {
    "id":17185,
    "value":22
  },
  {
    "id":17187,
    "value":130
  },
  {
    "id":17189,
    "value":19
  },
  {
    "id":17191,
    "value":11
  },
  {
    "id":17193,
    "value":3
  },
  {
    "id":17195,
    "value":178
  },
  {
    "id":17197,
    "value":6459
  },
  {
    "id":17199,
    "value":99
  },
  {
    "id":17201,
    "value":2911
  },
  {
    "id":17203,
    "value":32
  },
  {
    "id":80017,
    "value":1
  },
  {
    "id":90017,
    "value":45
  }
]