[
  {
    "id":17001,
    "value":46
  },
  {
    "id":17003,
    "value":18
  },
  {
    "id":17005,
    "value":12
  },
  {
    "id":17007,
    "value":546
  },
  {
    "id":17009,
    "value":10
  },
  {
    "id":17011,
    "value":24
  },
  {
    "id":17013,
    "value":1
  },
  {
    "id":17015,
    "value":18
  },
  {
    "id":17017,
    "value":79
  },
  {
    "id":17019,
    "value":761
  },
  {
    "id":17021,
    "value":42
  },
  {
    "id":17023,
    "value":13
  },
  {
    "id":17025,
    "value":3
  },
  {
    "id":17027,
    "value":220
  },
  {
    "id":17029,
    "value":146
  },
  {
    "id":17031,
    "value":86179
  },
  {
    "id":17033,
    "value":17
  },
  {
    "id":17035,
    "value":10
  },
  {
    "id":17037,
    "value":505
  },
  {
    "id":17039,
    "value":4
  },
  {
    "id":17041,
    "value":40
  },
  {
    "id":17043,
    "value":8574
  },
  {
    "id":17045,
    "value":3
  },
  {
    "id":17047,
    "value":2
  },
  {
    "id":17049,
    "value":12
  },
  {
    "id":17051,
    "value":23
  },
  {
    "id":17053,
    "value":22
  },
  {
    "id":17055,
    "value":12
  },
  {
    "id":17057,
    "value":12
  },
  {
    "id":17059,
    "value":2
  },
  {
    "id":17061,
    "value":8
  },
  {
    "id":17063,
    "value":139
  },
  {
    "id":17065,
    "value":2
  },
  {
    "id":17067,
    "value":18
  },
  {
    "id":17069,
    "value":1
  },
  {
    "id":17071,
    "value":8
  },
  {
    "id":17073,
    "value":72
  },
  {
    "id":17075,
    "value":142
  },
  {
    "id":17077,
    "value":321
  },
  {
    "id":17079,
    "value":46
  },
  {
    "id":17081,
    "value":104
  },
  {
    "id":17083,
    "value":29
  },
  {
    "id":17085,
    "value":35
  },
  {
    "id":17087,
    "value":20
  },
  {
    "id":17089,
    "value":7233
  },
  {
    "id":17091,
    "value":1121
  },
  {
    "id":17093,
    "value":899
  },
  {
    "id":17095,
    "value":115
  },
  {
    "id":17097,
    "value":9207
  },
  {
    "id":17099,
    "value":189
  },
  {
    "id":17101,
    "value":5
  },
  {
    "id":17103,
    "value":90
  },
  {
    "id":17105,
    "value":35
  },
  {
    "id":17107,
    "value":11
  },
  {
    "id":17109,
    "value":100
  },
  {
    "id":17111,
    "value":1884
  },
  {
    "id":17113,
    "value":246
  },
  {
    "id":17115,
    "value":214
  },
  {
    "id":17117,
    "value":46
  },
  {
    "id":17119,
    "value":771
  },
  {
    "id":17121,
    "value":55
  },
  {
    "id":17123,
    "value":5
  },
  {
    "id":17125,
    "value":18
  },
  {
    "id":17127,
    "value":7
  },
  {
    "id":17129,
    "value":23
  },
  {
    "id":17131,
    "value":19
  },
  {
    "id":17133,
    "value":110
  },
  {
    "id":17135,
    "value":41
  },
  {
    "id":17137,
    "value":118
  },
  {
    "id":17139,
    "value":15
  },
  {
    "id":17141,
    "value":230
  },
  {
    "id":17143,
    "value":411
  },
  {
    "id":17145,
    "value":44
  },
  {
    "id":17147,
    "value":17
  },
  {
    "id":17149,
    "value":2
  },
  {
    "id":17151,
    "value":1
  },
  {
    "id":17153,
    "value":65
  },
  {
    "id":17155,
    "value":1
  },
  {
    "id":17157,
    "value":279
  },
  {
    "id":17159,
    "value":4
  },
  {
    "id":17161,
    "value":766
  },
  {
    "id":17163,
    "value":1538
  },
  {
    "id":17165,
    "value":8
  },
  {
    "id":17167,
    "value":383
  },
  {
    "id":17169,
    "value":13
  },
  {
    "id":17171,
    "value":0
  },
  {
    "id":17173,
    "value":16
  },
  {
    "id":17175,
    "value":3
  },
  {
    "id":17177,
    "value":236
  },
  {
    "id":17179,
    "value":103
  },
  {
    "id":17181,
    "value":174
  },
  {
    "id":17183,
    "value":47
  },
  {
    "id":17185,
    "value":14
  },
  {
    "id":17187,
    "value":127
  },
  {
    "id":17189,
    "value":19
  },
  {
    "id":17191,
    "value":10
  },
  {
    "id":17193,
    "value":3
  },
  {
    "id":17195,
    "value":163
  },
  {
    "id":17197,
    "value":6256
  },
  {
    "id":17199,
    "value":91
  },
  {
    "id":17201,
    "value":2796
  },
  {
    "id":17203,
    "value":30
  },
  {
    "id":80017,
    "value":6
  },
  {
    "id":90017,
    "value":44
  }
]