[
  {
    "id":28001,
    "value":226
  },
  {
    "id":28003,
    "value":32
  },
  {
    "id":28005,
    "value":71
  },
  {
    "id":28007,
    "value":333
  },
  {
    "id":28009,
    "value":19
  },
  {
    "id":28011,
    "value":194
  },
  {
    "id":28013,
    "value":82
  },
  {
    "id":28015,
    "value":122
  },
  {
    "id":28017,
    "value":168
  },
  {
    "id":28019,
    "value":66
  },
  {
    "id":28021,
    "value":142
  },
  {
    "id":28023,
    "value":166
  },
  {
    "id":28025,
    "value":174
  },
  {
    "id":28027,
    "value":153
  },
  {
    "id":28029,
    "value":418
  },
  {
    "id":28031,
    "value":209
  },
  {
    "id":28033,
    "value":740
  },
  {
    "id":28035,
    "value":689
  },
  {
    "id":28037,
    "value":30
  },
  {
    "id":28039,
    "value":40
  },
  {
    "id":28041,
    "value":56
  },
  {
    "id":28043,
    "value":167
  },
  {
    "id":28045,
    "value":100
  },
  {
    "id":28047,
    "value":377
  },
  {
    "id":28049,
    "value":1349
  },
  {
    "id":28051,
    "value":474
  },
  {
    "id":28053,
    "value":83
  },
  {
    "id":28055,
    "value":0
  },
  {
    "id":28057,
    "value":106
  },
  {
    "id":28059,
    "value":378
  },
  {
    "id":28061,
    "value":200
  },
  {
    "id":28063,
    "value":54
  },
  {
    "id":28065,
    "value":84
  },
  {
    "id":28067,
    "value":899
  },
  {
    "id":28069,
    "value":170
  },
  {
    "id":28071,
    "value":195
  },
  {
    "id":28073,
    "value":292
  },
  {
    "id":28075,
    "value":816
  },
  {
    "id":28077,
    "value":120
  },
  {
    "id":28079,
    "value":491
  },
  {
    "id":28081,
    "value":310
  },
  {
    "id":28083,
    "value":376
  },
  {
    "id":28085,
    "value":329
  },
  {
    "id":28087,
    "value":335
  },
  {
    "id":28089,
    "value":905
  },
  {
    "id":28091,
    "value":152
  },
  {
    "id":28093,
    "value":110
  },
  {
    "id":28095,
    "value":297
  },
  {
    "id":28097,
    "value":98
  },
  {
    "id":28099,
    "value":895
  },
  {
    "id":28101,
    "value":324
  },
  {
    "id":28103,
    "value":216
  },
  {
    "id":28105,
    "value":374
  },
  {
    "id":28107,
    "value":137
  },
  {
    "id":28109,
    "value":223
  },
  {
    "id":28111,
    "value":54
  },
  {
    "id":28113,
    "value":247
  },
  {
    "id":28115,
    "value":79
  },
  {
    "id":28117,
    "value":68
  },
  {
    "id":28119,
    "value":51
  },
  {
    "id":28121,
    "value":550
  },
  {
    "id":28123,
    "value":692
  },
  {
    "id":28125,
    "value":8
  },
  {
    "id":28127,
    "value":123
  },
  {
    "id":28129,
    "value":182
  },
  {
    "id":28131,
    "value":34
  },
  {
    "id":28133,
    "value":127
  },
  {
    "id":28135,
    "value":45
  },
  {
    "id":28137,
    "value":135
  },
  {
    "id":28139,
    "value":95
  },
  {
    "id":28141,
    "value":47
  },
  {
    "id":28143,
    "value":67
  },
  {
    "id":28145,
    "value":108
  },
  {
    "id":28147,
    "value":107
  },
  {
    "id":28149,
    "value":262
  },
  {
    "id":28151,
    "value":269
  },
  {
    "id":28153,
    "value":398
  },
  {
    "id":28155,
    "value":109
  },
  {
    "id":28157,
    "value":85
  },
  {
    "id":28159,
    "value":155
  },
  {
    "id":28161,
    "value":139
  },
  {
    "id":28163,
    "value":350
  },
  {
    "id":80028,
    "value":0
  },
  {
    "id":90028,
    "value":0
  }
]