[
  {
    "id":37001,
    "value":1320
  },
  {
    "id":37003,
    "value":134
  },
  {
    "id":37005,
    "value":37
  },
  {
    "id":37007,
    "value":162
  },
  {
    "id":37009,
    "value":60
  },
  {
    "id":37011,
    "value":27
  },
  {
    "id":37013,
    "value":110
  },
  {
    "id":37015,
    "value":151
  },
  {
    "id":37017,
    "value":406
  },
  {
    "id":37019,
    "value":677
  },
  {
    "id":37021,
    "value":711
  },
  {
    "id":37023,
    "value":1129
  },
  {
    "id":37025,
    "value":1399
  },
  {
    "id":37027,
    "value":534
  },
  {
    "id":37029,
    "value":33
  },
  {
    "id":37031,
    "value":111
  },
  {
    "id":37033,
    "value":147
  },
  {
    "id":37035,
    "value":1018
  },
  {
    "id":37037,
    "value":999
  },
  {
    "id":37039,
    "value":48
  },
  {
    "id":37041,
    "value":30
  },
  {
    "id":37043,
    "value":14
  },
  {
    "id":37045,
    "value":407
  },
  {
    "id":37047,
    "value":570
  },
  {
    "id":37049,
    "value":405
  },
  {
    "id":37051,
    "value":1484
  },
  {
    "id":37053,
    "value":21
  },
  {
    "id":37055,
    "value":80
  },
  {
    "id":37057,
    "value":1114
  },
  {
    "id":37059,
    "value":251
  },
  {
    "id":37061,
    "value":1595
  },
  {
    "id":37063,
    "value":4176
  },
  {
    "id":37065,
    "value":352
  },
  {
    "id":37067,
    "value":3423
  },
  {
    "id":37069,
    "value":403
  },
  {
    "id":37071,
    "value":1443
  },
  {
    "id":37073,
    "value":27
  },
  {
    "id":37075,
    "value":10
  },
  {
    "id":37077,
    "value":854
  },
  {
    "id":37079,
    "value":192
  },
  {
    "id":37081,
    "value":3208
  },
  {
    "id":37083,
    "value":329
  },
  {
    "id":37085,
    "value":712
  },
  {
    "id":37087,
    "value":107
  },
  {
    "id":37089,
    "value":738
  },
  {
    "id":37091,
    "value":174
  },
  {
    "id":37093,
    "value":415
  },
  {
    "id":37095,
    "value":20
  },
  {
    "id":37097,
    "value":945
  },
  {
    "id":37099,
    "value":147
  },
  {
    "id":37101,
    "value":1789
  },
  {
    "id":37103,
    "value":39
  },
  {
    "id":37105,
    "value":875
  },
  {
    "id":37107,
    "value":391
  },
  {
    "id":37109,
    "value":334
  },
  {
    "id":37111,
    "value":280
  },
  {
    "id":37113,
    "value":293
  },
  {
    "id":37115,
    "value":17
  },
  {
    "id":37117,
    "value":150
  },
  {
    "id":37119,
    "value":13317
  },
  {
    "id":37121,
    "value":59
  },
  {
    "id":37123,
    "value":393
  },
  {
    "id":37125,
    "value":543
  },
  {
    "id":37127,
    "value":552
  },
  {
    "id":37129,
    "value":1260
  },
  {
    "id":37131,
    "value":203
  },
  {
    "id":37133,
    "value":364
  },
  {
    "id":37135,
    "value":848
  },
  {
    "id":37137,
    "value":26
  },
  {
    "id":37139,
    "value":225
  },
  {
    "id":37141,
    "value":303
  },
  {
    "id":37143,
    "value":37
  },
  {
    "id":37145,
    "value":123
  },
  {
    "id":37147,
    "value":844
  },
  {
    "id":37149,
    "value":89
  },
  {
    "id":37151,
    "value":1330
  },
  {
    "id":37153,
    "value":326
  },
  {
    "id":37155,
    "value":1429
  },
  {
    "id":37157,
    "value":271
  },
  {
    "id":37159,
    "value":1368
  },
  {
    "id":37161,
    "value":360
  },
  {
    "id":37163,
    "value":1122
  },
  {
    "id":37165,
    "value":152
  },
  {
    "id":37167,
    "value":481
  },
  {
    "id":37169,
    "value":147
  },
  {
    "id":37171,
    "value":525
  },
  {
    "id":37173,
    "value":67
  },
  {
    "id":37175,
    "value":37
  },
  {
    "id":37177,
    "value":19
  },
  {
    "id":37179,
    "value":1551
  },
  {
    "id":37181,
    "value":532
  },
  {
    "id":37183,
    "value":6299
  },
  {
    "id":37185,
    "value":174
  },
  {
    "id":37187,
    "value":41
  },
  {
    "id":37189,
    "value":104
  },
  {
    "id":37191,
    "value":1926
  },
  {
    "id":37193,
    "value":593
  },
  {
    "id":37195,
    "value":804
  },
  {
    "id":37197,
    "value":360
  },
  {
    "id":37199,
    "value":59
  },
  {
    "id":80037,
    "value":0
  },
  {
    "id":90037,
    "value":0
  }
]