[
  {
    "id":37001,
    "value":528
  },
  {
    "id":37003,
    "value":43
  },
  {
    "id":37005,
    "value":29
  },
  {
    "id":37007,
    "value":74
  },
  {
    "id":37009,
    "value":40
  },
  {
    "id":37011,
    "value":4
  },
  {
    "id":37013,
    "value":43
  },
  {
    "id":37015,
    "value":134
  },
  {
    "id":37017,
    "value":165
  },
  {
    "id":37019,
    "value":149
  },
  {
    "id":37021,
    "value":399
  },
  {
    "id":37023,
    "value":567
  },
  {
    "id":37025,
    "value":599
  },
  {
    "id":37027,
    "value":204
  },
  {
    "id":37029,
    "value":3
  },
  {
    "id":37031,
    "value":40
  },
  {
    "id":37033,
    "value":97
  },
  {
    "id":37035,
    "value":310
  },
  {
    "id":37037,
    "value":733
  },
  {
    "id":37039,
    "value":30
  },
  {
    "id":37041,
    "value":17
  },
  {
    "id":37043,
    "value":8
  },
  {
    "id":37045,
    "value":121
  },
  {
    "id":37047,
    "value":373
  },
  {
    "id":37049,
    "value":239
  },
  {
    "id":37051,
    "value":781
  },
  {
    "id":37053,
    "value":15
  },
  {
    "id":37055,
    "value":25
  },
  {
    "id":37057,
    "value":520
  },
  {
    "id":37059,
    "value":119
  },
  {
    "id":37061,
    "value":1047
  },
  {
    "id":37063,
    "value":2180
  },
  {
    "id":37065,
    "value":229
  },
  {
    "id":37067,
    "value":1816
  },
  {
    "id":37069,
    "value":190
  },
  {
    "id":37071,
    "value":366
  },
  {
    "id":37073,
    "value":24
  },
  {
    "id":37075,
    "value":4
  },
  {
    "id":37077,
    "value":513
  },
  {
    "id":37079,
    "value":104
  },
  {
    "id":37081,
    "value":1665
  },
  {
    "id":37083,
    "value":203
  },
  {
    "id":37085,
    "value":337
  },
  {
    "id":37087,
    "value":60
  },
  {
    "id":37089,
    "value":376
  },
  {
    "id":37091,
    "value":135
  },
  {
    "id":37093,
    "value":278
  },
  {
    "id":37095,
    "value":2
  },
  {
    "id":37097,
    "value":348
  },
  {
    "id":37099,
    "value":50
  },
  {
    "id":37101,
    "value":648
  },
  {
    "id":37103,
    "value":28
  },
  {
    "id":37105,
    "value":534
  },
  {
    "id":37107,
    "value":241
  },
  {
    "id":37109,
    "value":105
  },
  {
    "id":37111,
    "value":101
  },
  {
    "id":37113,
    "value":146
  },
  {
    "id":37115,
    "value":4
  },
  {
    "id":37117,
    "value":77
  },
  {
    "id":37119,
    "value":5682
  },
  {
    "id":37121,
    "value":17
  },
  {
    "id":37123,
    "value":165
  },
  {
    "id":37125,
    "value":259
  },
  {
    "id":37127,
    "value":242
  },
  {
    "id":37129,
    "value":270
  },
  {
    "id":37131,
    "value":165
  },
  {
    "id":37133,
    "value":134
  },
  {
    "id":37135,
    "value":405
  },
  {
    "id":37137,
    "value":13
  },
  {
    "id":37139,
    "value":119
  },
  {
    "id":37141,
    "value":113
  },
  {
    "id":37143,
    "value":26
  },
  {
    "id":37145,
    "value":61
  },
  {
    "id":37147,
    "value":397
  },
  {
    "id":37149,
    "value":48
  },
  {
    "id":37151,
    "value":801
  },
  {
    "id":37153,
    "value":184
  },
  {
    "id":37155,
    "value":905
  },
  {
    "id":37157,
    "value":116
  },
  {
    "id":37159,
    "value":771
  },
  {
    "id":37161,
    "value":200
  },
  {
    "id":37163,
    "value":621
  },
  {
    "id":37165,
    "value":98
  },
  {
    "id":37167,
    "value":118
  },
  {
    "id":37169,
    "value":86
  },
  {
    "id":37171,
    "value":279
  },
  {
    "id":37173,
    "value":25
  },
  {
    "id":37175,
    "value":16
  },
  {
    "id":37177,
    "value":4
  },
  {
    "id":37179,
    "value":592
  },
  {
    "id":37181,
    "value":370
  },
  {
    "id":37183,
    "value":2300
  },
  {
    "id":37185,
    "value":93
  },
  {
    "id":37187,
    "value":32
  },
  {
    "id":37189,
    "value":41
  },
  {
    "id":37191,
    "value":1335
  },
  {
    "id":37193,
    "value":511
  },
  {
    "id":37195,
    "value":445
  },
  {
    "id":37197,
    "value":217
  },
  {
    "id":37199,
    "value":21
  },
  {
    "id":80037,
    "value":0
  },
  {
    "id":90037,
    "value":0
  }
]