[
  {
    "id":36001,
    "value":1793
  },
  {
    "id":36003,
    "value":44
  },
  {
    "id":36005,
    "value":0
  },
  {
    "id":36007,
    "value":522
  },
  {
    "id":36009,
    "value":81
  },
  {
    "id":36011,
    "value":78
  },
  {
    "id":36013,
    "value":77
  },
  {
    "id":36015,
    "value":136
  },
  {
    "id":36017,
    "value":123
  },
  {
    "id":36019,
    "value":95
  },
  {
    "id":36021,
    "value":373
  },
  {
    "id":36023,
    "value":39
  },
  {
    "id":36025,
    "value":77
  },
  {
    "id":36027,
    "value":3834
  },
  {
    "id":36029,
    "value":5753
  },
  {
    "id":36031,
    "value":36
  },
  {
    "id":36033,
    "value":20
  },
  {
    "id":36035,
    "value":196
  },
  {
    "id":36037,
    "value":193
  },
  {
    "id":36039,
    "value":225
  },
  {
    "id":36041,
    "value":5
  },
  {
    "id":36043,
    "value":103
  },
  {
    "id":36045,
    "value":72
  },
  {
    "id":36047,
    "value":0
  },
  {
    "id":36049,
    "value":20
  },
  {
    "id":36051,
    "value":118
  },
  {
    "id":36053,
    "value":303
  },
  {
    "id":36055,
    "value":2762
  },
  {
    "id":36057,
    "value":80
  },
  {
    "id":36059,
    "value":39974
  },
  {
    "id":36061,
    "value":199301
  },
  {
    "id":36063,
    "value":965
  },
  {
    "id":36065,
    "value":917
  },
  {
    "id":36067,
    "value":2012
  },
  {
    "id":36069,
    "value":195
  },
  {
    "id":36071,
    "value":10277
  },
  {
    "id":36073,
    "value":208
  },
  {
    "id":36075,
    "value":104
  },
  {
    "id":36077,
    "value":69
  },
  {
    "id":36079,
    "value":1222
  },
  {
    "id":36081,
    "value":0
  },
  {
    "id":36083,
    "value":466
  },
  {
    "id":36085,
    "value":0
  },
  {
    "id":36087,
    "value":13019
  },
  {
    "id":36089,
    "value":197
  },
  {
    "id":36091,
    "value":463
  },
  {
    "id":36093,
    "value":668
  },
  {
    "id":36095,
    "value":49
  },
  {
    "id":36097,
    "value":11
  },
  {
    "id":36099,
    "value":55
  },
  {
    "id":36101,
    "value":240
  },
  {
    "id":36103,
    "value":39199
  },
  {
    "id":36105,
    "value":1338
  },
  {
    "id":36107,
    "value":122
  },
  {
    "id":36109,
    "value":154
  },
  {
    "id":36111,
    "value":1638
  },
  {
    "id":36113,
    "value":251
  },
  {
    "id":36115,
    "value":228
  },
  {
    "id":36117,
    "value":110
  },
  {
    "id":36119,
    "value":33107
  },
  {
    "id":36121,
    "value":82
  },
  {
    "id":36123,
    "value":37
  },
  {
    "id":80036,
    "value":0
  },
  {
    "id":90036,
    "value":0
  }
]