[
  {
    "id":56001,
    "value":74
  },
  {
    "id":56003,
    "value":33
  },
  {
    "id":56005,
    "value":101
  },
  {
    "id":56007,
    "value":59
  },
  {
    "id":56009,
    "value":30
  },
  {
    "id":56011,
    "value":9
  },
  {
    "id":56013,
    "value":440
  },
  {
    "id":56015,
    "value":11
  },
  {
    "id":56017,
    "value":16
  },
  {
    "id":56019,
    "value":22
  },
  {
    "id":56021,
    "value":400
  },
  {
    "id":56023,
    "value":72
  },
  {
    "id":56025,
    "value":184
  },
  {
    "id":56027,
    "value":2
  },
  {
    "id":56029,
    "value":95
  },
  {
    "id":56031,
    "value":5
  },
  {
    "id":56033,
    "value":40
  },
  {
    "id":56035,
    "value":18
  },
  {
    "id":56037,
    "value":206
  },
  {
    "id":56039,
    "value":254
  },
  {
    "id":56041,
    "value":227
  },
  {
    "id":56043,
    "value":45
  },
  {
    "id":56045,
    "value":4
  },
  {
    "id":80056,
    "value":0
  },
  {
    "id":90056,
    "value":0
  }
]